Workbook

Sheet dataset (2)
A1: Empresa | B1: Fecha | C1: P_E | D1: P_B | E1: P_S | F1: P_Share | G1: ROCE_sp | H1: ROCE_l | I1: EBIT_sp | J1: EBIT_l | K1: Total Activos_sp | L1: Total Activos_l | M1: Deuda a LP_sp | N1: Deuda a LP_l | O1: ROA_sp | P1: ROA_l | Q1: Beneficio neto_sp | R1: Beneficio neto_l | S1: ROI_sp | T1: ROI_l | U1: EV_sp | V1: EV_l | W1: Cap de mercado_sp | X1: Cap de mercado_l | Y1: Deuda a CP_sp | Z1: Deuda a CP_l | AA1: Efectivo y equiv_sp | AB1: Efectivo y equiv_l | AC1: CPI | AD1: CPI_Exp_mediana | AE1: CPI_Exp_promedio | AF1: Fed Funds Rate | AG1: Fed Funds Rate_Exp_mediana | AH1: Fed Funds Rate_Exp_promedio | AI1: Non farm payrolls | AJ1: Non farm payrolls_Exp_mediana | AK1: Non farm payrolls_Exp_promedio
A2: DLO US Equity | B2: 20220630 | C2: 106.0041 | D2: 27.6274 | E2: 30.8739 | F2: 26.25 | G2: 34.76 | H2: 34.76 | I2: 35.092 | J2: 35.092 | K2: 710.704 | L2: 710.704 | M2: 3.376 | N2: 3.376 | O2: 16.6244 | P2: 16.6244 | Q2: 30.572 | R2: 30.572 | S2: 32.58 | T2: 32.58 | U2: 3645.5968 | V2: 3645.5968 | W2: 7744.4966 | X2: 7744.4966 | Y2: 15.204 | Z2: 15.204 | AA2: 455.05 | AB2: 455.05 | AC2: 9.1 | AD2: 0.083 | AE2: 0.0826 | AF2: 1.75 | AG2: 0.015 | AH2: 0.0159 | AI2: 420 | AJ2: 318k | AK2: 323.49k
A3: DLO US Equity | B3: 20220729 | C3: 112.1826 | D3: 29.2377 | E3: 32.6734 | F3: 27.78 | G3: 36.348863 | H3: 35.071967 | I3: 40.691238 | J3: 35.805 | K3: 778.55932 | L3: 751.996 | M3: 3.42389 | N3: 3.4003333 | O3: 17.006031 | P3: 16.656933 | Q3: 37.031909 | R3: 31.202 | S3: 34.161168 | T3: 33.163633 | U3: 4768.6449 | V3: 4273.5528 | W3: 7361.9803 | X3: 7180.9923 | Y3: 19.557784 | Z3: 15.271667 | AA3: 525.87272 | AB3: 484.48767 | AC3: 8.5 | AD3: 0.088 | AE3: 0.0873 | AF3: 2.5 | AG3: 0.025 | AH3: 0.025 | AI3: 690 | AJ3: 265k | AK3: 264.67k
A4: DLO US Equity | B4: 20220831 | C4: 100.4313 | D4: 26.175 | E4: 29.2508 | F4: 24.87 | G4: 36.50909 | H4: 35.383933 | I4: 40.712946 | J4: 36.518 | K4: 817.47543 | L4: 793.288 | M4: 3.4463787 | N4: 3.4246667 | O4: 16.999767 | P4: 16.689467 | Q4: 36.829149 | R4: 31.832 | S4: 34.633832 | T4: 33.747267 | U4: 5370.3778 | V4: 4901.5088 | W4: 6756.8335 | X4: 6617.4879 | Y4: 19.099872 | Z4: 15.339333 | AA4: 550.63979 | AB4: 513.92533 | AC4: 8.3 | AD4: 0.087 | AE4: 0.0873 | AF4: 2.5 | AG4: 0.025 | AH4: 0.025 | AI4: 243 | AJ4: 250k | AK4: 234.73k
A5: DLO US Equity | B5: 20220930 | C5: 82.8649 | D5: 21.5968 | E5: 24.1346 | F5: 20.52 | G5: 35.6959 | H5: 35.6959 | I5: 37.231 | J5: 37.231 | K5: 834.58 | L5: 834.58 | M5: 3.449 | N5: 3.449 | O5: 16.722 | P5: 16.722 | Q5: 32.462 | R5: 32.462 | S5: 34.3309 | T5: 34.3309 | U5: 5529.4648 | V5: 5529.4648 | W5: 6053.9836 | X5: 6053.9836 | Y5: 15.407 | Z5: 15.407 | AA5: 543.363 | AB5: 543.363 | AC5: 8.2 | AD5: 0.081 | AE5: 0.0806 | AF5: 3.25 | AG5: 0.0325 | AH5: 0.0325 | AI5: 255 | AJ5: 298k | AK5: 294.94k
A6: DLO US Equity | B6: 20221031 | C6: 90.053 | D6: 23.4702 | E6: 26.2281 | F6: 22.3 | G6: 34.36451 | H6: 34.453267 | I6: 32.319276 | J6: 33.654667 | K6: 837.00068 | L6: 831.82033 | M6: 3.437288 | N6: 3.4303333 | O6: 16.289122 | P6: 16.2892 | Q6: 26.42874 | R6: 28.093667 | S6: 33.585279 | T6: 33.586467 | U6: 5324.5753 | V6: 5065.4912 | W6: 5378.3578 | X6: 5572.1517 | Y6: 10.055906 | Z6: 10.5 | AA6: 518.05409 | AB6: 518.70433 | AC6: 7.7 | AD6: 0.081 | AE6: 0.0809 | AF6: 3.25 | AG6: 0.0325 | AH6: 0.0325 | AI6: 361 | AJ6: 255k | AK6: 264.77k
A7: DLO US Equity | B7: 20221130 | C7: 58.9585 | D7: 15.3661 | E7: 17.1718 | F7: 14.6 | G7: 32.970137 | H7: 33.210633 | I7: 28.051651 | J7: 30.078333 | K7: 831.86513 | L7: 829.06067 | M7: 3.4167766 | N7: 3.4116667 | O7: 15.817524 | P7: 15.8564 | Q7: 21.227647 | R7: 23.725333 | S7: 32.729877 | T7: 32.842033 | U7: 4834.3786 | V7: 4601.5176 | W7: 4854.8835 | X7: 5090.3198 | Y7: 4.6233266 | Z7: 5.593 | AA7: 488.72484 | AB7: 494.04567 | AC7: 7.1 | AD7: 0.079 | AE7: 0.0795 | AF7: 4 | AG7: 0.04 | AH7: 0.0399 | AI7: 258 | AJ7: 193k | AK7: 197.14k
A8: DLO US Equity | B8: 20221230 | C8: 62.8756 | D8: 16.387 | E8: 18.3126 | F8: 15.57 | G8: 31.968 | H8: 31.968 | I8: 26.502 | J8: 26.502 | K8: 826.301 | L8: 826.301 | M8: 3.393 | N8: 3.393 | O8: 15.4236 | P8: 15.4236 | Q8: 19.357 | R8: 19.357 | S8: 32.0976 | T8: 32.0976 | U8: 4137.544 | V8: 4137.544 | W8: 4608.4879 | X8: 4608.4879 | Y8: 0.686 | Z8: 0.686 | AA8: 469.387 | AB8: 469.387 | AC8: 6.5 | AD8: 0.073 | AE8: 0.073 | AF8: 4.5 | AG8: 0.045 | AH8: 0.045 | AI8: 136 | AJ8: 200k | AK8: 195.44k
A9: DLO US Equity | B9: 20230131 | C9: 45.072 | D9: 12.2724 | E9: 11.7071 | F9: 16.59 | G9: 31.710461 | H9: 32.342033 | I9: 29.020472 | J9: 30.787667 | K9: 827.14029 | L9: 840.97767 | M9: 3.3699951 | N9: 3.3676667 | O9: 15.197264 | P9: 15.3347 | Q9: 22.453355 | R9: 24.719333 | S9: 31.94113 | T9: 32.299233 | U9: 3331.94 | V9: 3462.4563 | W9: 4690.7587 | X9: 4672.618 | Y9: -0.65837043 | Z9: 0.68366667 | AA9: 470.60017 | AB9: 485.66833 | AC9: 6.4 | AD9: 0.065 | AE9: 0.0649 | AF9: 4.5 | AG9: 0.045 | AH9: 0.045 | AI9: 482 | AJ9: 205k | AK9: 207.43k
A10: DLO US Equity | B10: 20230228 | C10: 40.5892 | D10: 11.0518 | E10: 10.5427 | F10: 14.94 | G10: 32.138464 | H10: 32.716067 | I10: 34.062303 | J10: 35.073333 | K10: 840.03239 | L10: 855.65433 | M10: 3.345811 | N10: 3.3423333 | O10: 15.122521 | P10: 15.2458 | Q10: 28.706374 | R10: 30.081667 | S10: 32.192246 | T10: 32.500867 | U10: 2592.231 | V10: 2787.3685 | W10: 4859.9255 | X10: 4736.7481 | Y10: -0.22821558 | Z10: 0.68133333 | AA10: 489.11525 | AB10: 501.94967 | AC10: 6 | AD10: 0.062 | AE10: 0.0624 | AF10: 4.75 | AG10: 0.0475 | AH10: 0.0475 | AI10: 287 | AJ10: 189k | AK10: 198.04k
A11: DLO US Equity | B11: 20230331 | C11: 44.0667 | D11: 11.9987 | E11: 11.446 | F11: 16.22 | G11: 33.0901 | H11: 33.0901 | I11: 39.359 | J11: 39.359 | K11: 870.331 | L11: 870.331 | M11: 3.317 | N11: 3.317 | O11: 15.1569 | P11: 15.1569 | Q11: 35.444 | R11: 35.444 | S11: 32.7025 | T11: 32.7025 | U11: 2112.2808 | V11: 2112.2808 | W11: 4800.8782 | X11: 4800.8782 | Y11: 0.679 | Z11: 0.679 | AA11: 518.231 | AB11: 518.231 | AC11: 5 | AD11: 0.06 | AE11: 0.0604 | AF11: 5 | AG11: 0.05 | AH11: 0.0497 | AI11: 146 | AJ11: 225k | AK11: 223.44k
A12: DLO US Equity | B12: 20230428 | C12: 38.0354 | D12: 10.3564 | E12: 9.8794 | F12: 14 | G12: 34.351128 | H12: 34.078333 | I12: 43.148502 | J12: 42.161667 | K12: 919.3004 | L12: 916.48333 | M12: 3.2846946 | N12: 3.3086667 | O12: 15.252693 | P12: 15.220833 | Q12: 40.470212 | R12: 38.528333 | S12: 33.303947 | T12: 33.060733 | U12: 2040.1658 | V12: 2385.9766 | W12: 4328.6169 | X12: 4406.0266 | Y12: 1.0393908 | Z12: 0.67766667 | AA12: 551.20101 | AB12: 545.80433 | AC12: 4.9 | AD12: 0.051 | AE12: 0.0516 | AF12: 5 | AG12: 0.05 | AH12: 0.0497 | AI12: 278 | AJ12: 230k | AK12: 224.31k
A13: DLO US Equity | B13: 20230531 | C13: 31.6237 | D13: 8.6106 | E13: 8.214 | F13: 11.64 | G13: 35.497991 | H13: 35.066567 | I13: 45.69447 | J13: 44.964333 | K13: 971.84706 | L13: 962.63567 | M13: 3.2683496 | N13: 3.3003333 | O13: 15.341254 | P13: 15.284767 | Q13: 43.493152 | R13: 41.612667 | S13: 33.750657 | T13: 33.418967 | U13: 2340.8145 | V13: 2659.6723 | W13: 3778.5819 | X13: 4011.175 | Y13: 0.92338755 | Z13: 0.67633333 | AA13: 581.09837 | AB13: 573.37767 | AC13: 4 | AD13: 0.05 | AE13: 0.05 | AF13: 5.25 | AG13: 0.0525 | AH13: 0.0523 | AI13: 303 | AJ13: 185k | AK13: 185.59k
... A29: DLO US Equity | B29: 20240930 | C29: 25.3674 | D29: 5.0908 | E29: 3.5917 | F29: 8 | G29: 26.8701 | H29: 26.8701 | I29: 41.136 | J29: 41.136 | K29: 1171.159 | L29: 1171.159 | M29: 2.985 | N29: 2.985 | O29: 10.9467 | P29: 10.9467 | Q29: 26.782 | R29: 26.782 | S29: 24.568 | T29: 24.568 | U29: 1612.8669 | V29: 1612.8669 | W29: 2367.9333 | X29: 2367.9333 | Y29: 1.127 | Z29: 1.127 | AA29: 672.779 | AB29: 672.779 | AC29: 2.4 | AD29: 0.025 | AE29: 0.0255 | AF29: 5 | AG29: 0.0525 | AH29: 0.0523 | AI29: 223 | AJ29: 165k | AK29: 162.83k

Sheet dataset
A1: Empresa | B1: Fecha | C1: P_E | D1: P_B | E1: P_S | F1: P_Share | G1: ROCE_sp | H1: ROCE_l | I1: EBIT_sp | J1: EBIT_l | K1: Total Activos_sp | L1: Total Activos_l | M1: Deuda a LP_sp | N1: Deuda a LP_l | O1: ROA_sp | P1: ROA_l | Q1: Beneficio neto_sp | R1: Beneficio neto_l | S1: ROI_sp | T1: ROI_l | U1: EV_sp | V1: EV_l | W1: Cap de mercado_sp | X1: Cap de mercado_l | Y1: Deuda a CP_sp | Z1: Deuda a CP_l | AA1: Efectivo y equiv_sp | AB1: Efectivo y equiv_l | AC1: CPI | AD1: CPI_Exp_mediana | AE1: CPI_Exp_promedio | AF1: Fed Funds Rate | AG1: Fed Funds Rate_Exp_mediana | AH1: Fed Funds Rate_Exp_promedio | AI1: Non farm payrolls | AJ1: Non farm payrolls_Exp_mediana | AK1: Non farm payrolls_Exp_promedio
A2: DLO US Equity | B2: 20220630 | C2: 106.0041 | D2: 27.6274 | E2: 30.8739 | F2: 26.25 | G2: 34.76 | H2: 34.76 | I2: 35.092 | J2: 35.092 | K2: 710.704 | L2: 710.704 | M2: 3.376 | N2: 3.376 | O2: 16.6244 | P2: 16.6244 | Q2: 30.572 | R2: 30.572 | S2: 32.58 | T2: 32.58 | U2: 3645.5968 | V2: 3645.5968 | W2: 7744.4966 | X2: 7744.4966 | Y2: 15.204 | Z2: 15.204 | AA2: 455.05 | AB2: 455.05 | AC2: 9.1 | AD2: 0.083 | AE2: 0.0826 | AF2: 1.75 | AG2: 0.015 | AH2: 0.0159 | AI2: 420 | AJ2: 318k | AK2: 323.49k
A3: DLO US Equity | B3: 20220729 | C3: 112.1826 | D3: 29.2377 | E3: 32.6734 | F3: 27.78 | G3: 36.351442 | H3: 35.071967 | I3: 37.263395 | J3: 35.805 | K3: 749.71035 | L3: 751.996 | M3: 3.4017717 | N3: 3.4003333 | O3: 17.007002 | P3: 16.656933 | Q3: 32.759417 | R3: 31.202 | S3: 34.163069 | T3: 33.163633 | U3: 4350.4582 | V3: 4273.5528 | W3: 7187.1242 | X3: 7180.9923 | Y3: 17.249861 | Z3: 15.271667 | AA3: 490.76983 | AB3: 484.48767 | AC3: 8.5 | AD3: 0.088 | AE3: 0.0873 | AF3: 2.5 | AG3: 0.025 | AH3: 0.025 | AI3: 690 | AJ3: 265k | AK3: 264.67k
A4: DLO US Equity | B4: 20220831 | C4: 100.4313 | D4: 26.175 | E4: 29.2508 | F4: 24.87 | G4: 36.511153 | H4: 35.383933 | I4: 38.391658 | J4: 36.518 | K4: 797.94019 | L4: 793.288 | M4: 3.4313937 | N4: 3.4246667 | O4: 17.000544 | P4: 16.689467 | Q4: 33.936084 | R4: 31.832 | S4: 34.635353 | T4: 33.747267 | U4: 5087.1158 | V4: 4901.5088 | W4: 6638.4024 | X4: 6617.4879 | Y4: 17.536895 | Z4: 15.339333 | AA4: 526.86706 | AB4: 513.92533 | AC4: 8.3 | AD4: 0.087 | AE4: 0.0873 | AF4: 2.5 | AG4: 0.025 | AH4: 0.025 | AI4: 243 | AJ4: 250k | AK4: 234.73k
A5: DLO US Equity | B5: 20220930 | C5: 82.8649 | D5: 21.5968 | E5: 24.1346 | F5: 20.52 | G5: 35.6959 | H5: 35.6959 | I5: 37.231 | J5: 37.231 | K5: 834.58 | L5: 834.58 | M5: 3.449 | N5: 3.449 | O5: 16.722 | P5: 16.722 | Q5: 32.462 | R5: 32.462 | S5: 34.3309 | T5: 34.3309 | U5: 5529.4648 | V5: 5529.4648 | W5: 6053.9836 | X5: 6053.9836 | Y5: 15.407 | Z5: 15.407 | AA5: 543.363 | AB5: 543.363 | AC5: 8.2 | AD5: 0.081 | AE5: 0.0806 | AF5: 3.25 | AG5: 0.0325 | AH5: 0.0325 | AI5: 255 | AJ5: 298k | AK5: 294.94k
A6: DLO US Equity | B6: 20221031 | C6: 90.053 | D6: 23.4702 | E6: 26.2281 | F6: 22.3 | G6: 34.362447 | H6: 34.453267 | I6: 33.237274 | J6: 33.654667 | K6: 844.72282 | L6: 831.82033 | M6: 3.4432406 | N6: 3.4303333 | O6: 16.288345 | P6: 16.2892 | Q6: 27.572044 | R6: 28.093667 | S6: 33.583758 | T6: 33.586467 | U6: 5436.8793 | V6: 5065.4912 | W6: 5425.2762 | X6: 5572.1517 | Y6: 10.674344 | Z6: 10.5 | AA6: 527.46155 | AB6: 518.70433 | AC6: 7.7 | AD6: 0.081 | AE6: 0.0809 | AF6: 3.25 | AG6: 0.0325 | AH6: 0.0325 | AI6: 361 | AJ6: 255k | AK6: 264.77k
A7: DLO US Equity | B7: 20221130 | C7: 58.9585 | D7: 15.3661 | E7: 17.1718 | F7: 14.6 | G7: 32.967558 | H7: 33.210633 | I7: 28.672915 | J7: 30.078333 | K7: 837.08789 | L7: 829.06067 | M7: 3.4208303 | N7: 3.4116667 | O7: 15.816553 | P7: 15.8564 | Q7: 22.000617 | R7: 23.725333 | S7: 32.727976 | T7: 32.842033 | U7: 4910.6494 | V7: 4601.5176 | W7: 4886.7142 | X7: 5090.3198 | Y7: 5.0421728 | Z7: 5.593 | AA7: 495.09719 | AB7: 494.04567 | AC7: 7.1 | AD7: 0.079 | AE7: 0.0795 | AF7: 4 | AG7: 0.04 | AH7: 0.0399 | AI7: 258 | AJ7: 193k | AK7: 197.14k
A8: DLO US Equity | B8: 20221230 | C8: 62.8756 | D8: 16.387 | E8: 18.3126 | F8: 15.57 | G8: 31.968 | H8: 31.968 | I8: 26.502 | J8: 26.502 | K8: 826.301 | L8: 826.301 | M8: 3.393 | N8: 3.393 | O8: 15.4236 | P8: 15.4236 | Q8: 19.357 | R8: 19.357 | S8: 32.0976 | T8: 32.0976 | U8: 4137.544 | V8: 4137.544 | W8: 4608.4879 | X8: 4608.4879 | Y8: 0.686 | Z8: 0.686 | AA8: 469.387 | AB8: 469.387 | AC8: 6.5 | AD8: 0.073 | AE8: 0.073 | AF8: 4.5 | AG8: 0.045 | AH8: 0.045 | AI8: 136 | AJ8: 200k | AK8: 195.44k
A9: DLO US Equity | B9: 20230131 | C9: 45.072 | D9: 12.2724 | E9: 11.7071 | F9: 16.59 | G9: 31.716135 | H9: 32.342033 | I9: 28.776323 | J9: 30.787667 | K9: 825.1007 | L9: 840.97767 | M9: 3.368303 | N9: 3.3676667 | O9: 15.1994 | P9: 15.3347 | Q9: 22.15263 | R9: 24.719333 | S9: 31.945313 | T9: 32.299233 | U9: 3300.9104 | V9: 3462.4563 | W9: 4677.9413 | X9: 4672.618 | Y9: -0.82420105 | Z9: 0.68366667 | AA9: 468.07323 | AB9: 485.66833 | AC9: 6.4 | AD9: 0.065 | AE9: 0.0649 | AF9: 4.5 | AG9: 0.045 | AH9: 0.045 | AI9: 482 | AJ9: 205k | AK9: 207.43k
A10: DLO US Equity | B10: 20230228 | C10: 40.5892 | D10: 11.0518 | E10: 10.5427 | F10: 14.94 | G10: 32.146717 | H10: 32.716067 | I10: 33.898535 | J10: 35.073333 | K10: 838.67658 | L10: 855.65433 | M10: 3.3445815 | N10: 3.3423333 | O10: 15.125628 | P10: 15.2458 | Q10: 28.50756 | R10: 30.081667 | S10: 32.198329 | T10: 32.500867 | U10: 2570.4096 | V10: 2787.3685 | W10: 4851.0337 | X10: 4736.7481 | Y10: -0.34062303 | Z10: 0.68133333 | AA10: 487.3986 | AB10: 501.94967 | AC10: 6 | AD10: 0.062 | AE10: 0.0624 | AF10: 4.75 | AG10: 0.0475 | AH10: 0.0475 | AI10: 287 | AJ10: 189k | AK10: 198.04k
A11: DLO US Equity | B11: 20230331 | C11: 44.0667 | D11: 11.9987 | E11: 11.446 | F11: 16.22 | G11: 33.0901 | H11: 33.0901 | I11: 39.359 | J11: 39.359 | K11: 870.331 | L11: 870.331 | M11: 3.317 | N11: 3.317 | O11: 15.1569 | P11: 15.1569 | Q11: 35.444 | R11: 35.444 | S11: 32.7025 | T11: 32.7025 | U11: 2112.2808 | V11: 2112.2808 | W11: 4800.8782 | X11: 4800.8782 | Y11: 0.679 | Z11: 0.679 | AA11: 518.231 | AB11: 518.231 | AC11: 5 | AD11: 0.06 | AE11: 0.0604 | AF11: 5 | AG11: 0.05 | AH11: 0.0497 | AI11: 146 | AJ11: 225k | AK11: 223.44k
A12: DLO US Equity | B12: 20230428 | C12: 38.0354 | D12: 10.3564 | E12: 9.8794 | F12: 14 | G12: 34.330496 | H12: 34.078333 | I12: 43.207099 | J12: 42.161667 | K12: 919.73666 | L12: 916.48333 | M12: 3.2855105 | N12: 3.3086667 | O12: 15.244925 | P12: 15.220833 | Q12: 40.529807 | R12: 38.528333 | S12: 33.288739 | T12: 33.060733 | U12: 2051.9799 | V12: 2385.9766 | W12: 4332.9682 | X12: 4406.0266 | Y12: 1.0842748 | Z12: 0.67766667 | AA12: 551.90132 | AB12: 545.80433 | AC12: 4.9 | AD12: 0.051 | AE12: 0.0516 | AF12: 5 | AG12: 0.05 | AH12: 0.0497 | AI12: 278 | AJ12: 230k | AK12: 224.31k
A13: DLO US Equity | B13: 20230531 | C13: 31.6237 | D13: 8.6106 | E13: 8.214 | F13: 11.64 | G13: 35.467559 | H13: 35.066567 | I13: 45.728278 | J13: 44.964333 | K13: 972.04755 | L13: 962.63567 | M13: 3.2692143 | N13: 3.3003333 | O13: 15.329796 | P13: 15.284767 | Q13: 43.515438 | R13: 41.612667 | S13: 33.728225 | T13: 33.418967 | U13: 2351.8293 | V13: 2659.6723 | W13: 3782.3184 | X13: 4011.175 | Y13: 0.95417123 | Z13: 0.67633333 | AA13: 581.59263 | AB13: 573.37767 | AC13: 4 | AD13: 0.05 | AE13: 0.05 | AF13: 5.25 | AG13: 0.0525 | AH13: 0.0523 | AI13: 303 | AJ13: 185k | AK13: 185.59k
... A23: DLO US Equity | B23: 20240329 | C23: 46.6127 | D23: 9.3543 | E23: 6.5997 | F23: 14.7 | G23: 29.8699 | H23: 29.8699 | I23: 26.901 | J23: 26.901 | K23: 1156 | L23: 1156 | M23: 3.163 | N23: 3.163 | O23: 12.9523 | P23: 12.9523 | Q23: 17.708 | R23: 17.708 | S23: 29.0969 | T23: 29.0969 | U23: 3674.9177 | V23: 3674.9177 | W23: 4351.0775 | X23: 4351.0775 | Y23: 0.699 | Z23: 0.699 | AA23: 680.134 | AB23: 680.134 | AC23: 3.5 | AD23: 0.031 | AE23: 0.0311 | AF23: 5.5 | AG23: 0.055 | AH23: 0.055 | AI23: 310 | AJ23: 200k | AK23: 198.20k
A24: DLO US Equity | B24: 20240430 | C24: 45.0589 | D24: 9.0425 | E24: 6.3797 | F24: 14.21 | Q24: 20.567072 | R24: 27.22 | W24: 3964.9159 | X24: 3698.9092 | AC24: 3.4 | AD24: 0.034 | AE24: 0.0342 | AF24: 5.5 | AG24: 0.055 | AH24: 0.055 | AI24: 108 | AJ24: 214k | AK24: 209.72k
A25: DLO US Equity | B25: 20240531 | C25: 29.014 | D25: 5.8226 | E25: 4.108 | F25: 9.15 | Q25: 29.508701 | R25: 36.732 | W25: 3346.3242 | X25: 3046.7409 | AC25: 3.3 | AD25: 0.034 | AE25: 0.034 | AF25: 5.5 | AG25: 0.055 | AH25: 0.055 | AI25: 216 | AJ25: 240k | AK25: 234.25k
A26: DLO US Equity | B26: 20240628 | C26: 25.6528 | D26: 5.1481 | E26: 3.6321 | F26: 8.09 | G26: 31.948 | H26: 31.948 | I26: 30.195 | J26: 30.195 | K26: 1195.684 | L26: 1195.684 | M26: 3.106 | N26: 3.106 | O26: 12.046 | P26: 12.046 | Q26: 46.244 | R26: 46.244 | S26: 26.9106 | T26: 26.9106 | U26: 1674.8219 | V26: 1674.8219 | W26: 2394.5726 | X26: 2394.5726 | Y26: 0.782 | Z26: 0.782 | AA26: 651.917 | AC26: 3 | AD26: 0.034 | AE26: 0.0338 | AF26: 5.5 | AG26: 0.055 | AH26: 0.055 | AI26: 118 | AJ26: 180k | AK26: 183.69k
A27: DLO US Equity | B27: 20240731 | C27: 24.3527 | D27: 4.8872 | E27: 3.448 | F27: 7.68 | AC27: 2.9 | AD27: 0.031 | AE27: 0.031 | AF27: 5.5 | AG27: 0.055 | AH27: 0.055 | AI27: 144 | AJ27: 190k | AK27: 191.20k
A28: DLO US Equity | B28: 20240830 | C28: 28.2847 | D28: 5.6762 | E28: 4.0047 | F28: 8.92 | AC28: 2.5 | AD28: 0.03 | AE28: 0.0297 | AF28: 5.5 | AG28: 0.055 | AH28: 0.055 | AI28: 78 | AJ28: 175k | AK28: 175.07k
A29: DLO US Equity | B29: 20240930 | C29: 25.3674 | D29: 5.0908 | E29: 3.5917 | F29: 8 | G29: 26.8701 | H29: 26.8701 | I29: 41.136 | J29: 41.136 | K29: 1171.159 | L29: 1171.159 | M29: 2.985 | N29: 2.985 | O29: 10.9467 | P29: 10.9467 | Q29: 26.782 | R29: 26.782 | S29: 24.568 | T29: 24.568 | U29: 1612.8669 | V29: 1612.8669 | W29: 2367.9333 | X29: 2367.9333 | Y29: 1.127 | Z29: 1.127 | AA29: 672.779 | AC29: 2.4 | AD29: 0.025 | AE29: 0.0255 | AF29: 5 | AG29: 0.0525 | AH29: 0.0523 | AI29: 223 | AJ29: 165k | AK29: 162.83k
U32: FQ1 2024
U33: 3677.5625
U35: =+U33-U23 -> 2.6448

Sheet Hoja2
C2: =+dataset!C2-'dataset (2)'!C2 -> 0 | D2: =+dataset!D2-'dataset (2)'!D2 -> 0 | E2: =+dataset!E2-'dataset (2)'!E2 -> 0 | F2: =+dataset!F2-'dataset (2)'!F2 -> 0 | G2: =+dataset!G2-'dataset (2)'!G2 -> 0 | H2: =+dataset!H2-'dataset (2)'!H2 -> 0 | I2: =+dataset!I2-'dataset (2)'!I2 -> 0 | J2: =+dataset!J2-'dataset (2)'!J2 -> 0 | ... AE2: =+dataset!AE2-'dataset (2)'!AE2 -> 0
C3: =+dataset!C3-'dataset (2)'!C3 -> 0 | D3: =+dataset!D3-'dataset (2)'!D3 -> 0 | E3: =+dataset!E3-'dataset (2)'!E3 -> 0 | F3: =+dataset!F3-'dataset (2)'!F3 -> 0 | G3: =+dataset!G3-'dataset (2)'!G3 -> 0.0025790165 | H3: =+dataset!H3-'dataset (2)'!H3 -> 0 | I3: =+dataset!I3-'dataset (2)'!I3 -> -3.4278433 | J3: =+dataset!J3-'dataset (2)'!J3 -> 0 | ... AE3: =+dataset!AE3-'dataset (2)'!AE3 -> 0
C4: =+dataset!C4-'dataset (2)'!C4 -> 0 | D4: =+dataset!D4-'dataset (2)'!D4 -> 0 | E4: =+dataset!E4-'dataset (2)'!E4 -> 0 | F4: =+dataset!F4-'dataset (2)'!F4 -> 0 | G4: =+dataset!G4-'dataset (2)'!G4 -> 0.0020632132 | H4: =+dataset!H4-'dataset (2)'!H4 -> 0 | I4: =+dataset!I4-'dataset (2)'!I4 -> -2.3212877 | J4: =+dataset!J4-'dataset (2)'!J4 -> 0 | ... AE4: =+dataset!AE4-'dataset (2)'!AE4 -> 0
C5: =+dataset!C5-'dataset (2)'!C5 -> 0 | D5: =+dataset!D5-'dataset (2)'!D5 -> 0 | E5: =+dataset!E5-'dataset (2)'!E5 -> 0 | F5: =+dataset!F5-'dataset (2)'!F5 -> 0 | G5: =+dataset!G5-'dataset (2)'!G5 -> 0 | H5: =+dataset!H5-'dataset (2)'!H5 -> 0 | I5: =+dataset!I5-'dataset (2)'!I5 -> 0 | J5: =+dataset!J5-'dataset (2)'!J5 -> 0 | ... AE5: =+dataset!AE5-'dataset (2)'!AE5 -> 0
C6: =+dataset!C6-'dataset (2)'!C6 -> 0 | D6: =+dataset!D6-'dataset (2)'!D6 -> 0 | E6: =+dataset!E6-'dataset (2)'!E6 -> 0 | F6: =+dataset!F6-'dataset (2)'!F6 -> 0 | G6: =+dataset!G6-'dataset (2)'!G6 -> -0.0020632132 | H6: =+dataset!H6-'dataset (2)'!H6 -> 0 | I6: =+dataset!I6-'dataset (2)'!I6 -> 0.91799803 | J6: =+dataset!J6-'dataset (2)'!J6 -> 0 | ... AE6: =+dataset!AE6-'dataset (2)'!AE6 -> 0
C7: =+dataset!C7-'dataset (2)'!C7 -> 0 | D7: =+dataset!D7-'dataset (2)'!D7 -> 0 | E7: =+dataset!E7-'dataset (2)'!E7 -> 0 | F7: =+dataset!F7-'dataset (2)'!F7 -> 0 | G7: =+dataset!G7-'dataset (2)'!G7 -> -0.0025790165 | H7: =+dataset!H7-'dataset (2)'!H7 -> 0 | I7: =+dataset!I7-'dataset (2)'!I7 -> 0.6212639 | J7: =+dataset!J7-'dataset (2)'!J7 -> 0 | ... AE7: =+dataset!AE7-'dataset (2)'!AE7 -> 0
C8: =+dataset!C8-'dataset (2)'!C8 -> 0 | D8: =+dataset!D8-'dataset (2)'!D8 -> 0 | E8: =+dataset!E8-'dataset (2)'!E8 -> 0 | F8: =+dataset!F8-'dataset (2)'!F8 -> 0 | G8: =+dataset!G8-'dataset (2)'!G8 -> 0 | H8: =+dataset!H8-'dataset (2)'!H8 -> 0 | I8: =+dataset!I8-'dataset (2)'!I8 -> 0 | J8: =+dataset!J8-'dataset (2)'!J8 -> 0 | ... AE8: =+dataset!AE8-'dataset (2)'!AE8 -> 0
C9: =+dataset!C9-'dataset (2)'!C9 -> 0 | D9: =+dataset!D9-'dataset (2)'!D9 -> 0 | E9: =+dataset!E9-'dataset (2)'!E9 -> 0 | F9: =+dataset!F9-'dataset (2)'!F9 -> 0 | G9: =+dataset!G9-'dataset (2)'!G9 -> 0.0056738362 | H9: =+dataset!H9-'dataset (2)'!H9 -> 0 | I9: =+dataset!I9-'dataset (2)'!I9 -> -0.2441488 | J9: =+dataset!J9-'dataset (2)'!J9 -> 0 | ... AE9: =+dataset!AE9-'dataset (2)'!AE9 -> 0
C10: =+dataset!C10-'dataset (2)'!C10 -> 0 | D10: =+dataset!D10-'dataset (2)'!D10 -> 0 | E10: =+dataset!E10-'dataset (2)'!E10 -> 0 | F10: =+dataset!F10-'dataset (2)'!F10 -> 0 | G10: =+dataset!G10-'dataset (2)'!G10 -> 0.0082528527 | H10: =+dataset!H10-'dataset (2)'!H10 -> 0 | I10: =+dataset!I10-'dataset (2)'!I10 -> -0.16376784 | J10: =+dataset!J10-'dataset (2)'!J10 -> 0 | ... AE10: =+dataset!AE10-'dataset (2)'!AE10 -> 0
C11: =+dataset!C11-'dataset (2)'!C11 -> 0 | D11: =+dataset!D11-'dataset (2)'!D11 -> 0 | E11: =+dataset!E11-'dataset (2)'!E11 -> 0 | F11: =+dataset!F11-'dataset (2)'!F11 -> 0 | G11: =+dataset!G11-'dataset (2)'!G11 -> 0 | H11: =+dataset!H11-'dataset (2)'!H11 -> 0 | I11: =+dataset!I11-'dataset (2)'!I11 -> 0 | J11: =+dataset!J11-'dataset (2)'!J11 -> 0 | ... AE11: =+dataset!AE11-'dataset (2)'!AE11 -> 0
C12: =+dataset!C12-'dataset (2)'!C12 -> 0 | D12: =+dataset!D12-'dataset (2)'!D12 -> 0 | E12: =+dataset!E12-'dataset (2)'!E12 -> 0 | F12: =+dataset!F12-'dataset (2)'!F12 -> 0 | G12: =+dataset!G12-'dataset (2)'!G12 -> -0.020632132 | H12: =+dataset!H12-'dataset (2)'!H12 -> 0 | I12: =+dataset!I12-'dataset (2)'!I12 -> 0.058597163 | J12: =+dataset!J12-'dataset (2)'!J12 -> 0 | ... AE12: =+dataset!AE12-'dataset (2)'!AE12 -> 0
C13: =+dataset!C13-'dataset (2)'!C13 -> 0 | D13: =+dataset!D13-'dataset (2)'!D13 -> 0 | E13: =+dataset!E13-'dataset (2)'!E13 -> 0 | F13: =+dataset!F13-'dataset (2)'!F13 -> 0 | G13: =+dataset!G13-'dataset (2)'!G13 -> -0.030432394 | H13: =+dataset!H13-'dataset (2)'!H13 -> 0 | I13: =+dataset!I13-'dataset (2)'!I13 -> 0.033807451 | J13: =+dataset!J13-'dataset (2)'!J13 -> 0 | ... AE13: =+dataset!AE13-'dataset (2)'!AE13 -> 0
... C29: =+dataset!C29-'dataset (2)'!C29 -> 0 | D29: =+dataset!D29-'dataset (2)'!D29 -> 0 | E29: =+dataset!E29-'dataset (2)'!E29 -> 0 | F29: =+dataset!F29-'dataset (2)'!F29 -> 0 | G29: =+dataset!G29-'dataset (2)'!G29 -> 0 | H29: =+dataset!H29-'dataset (2)'!H29 -> 0 | I29: =+dataset!I29-'dataset (2)'!I29 -> 0 | J29: =+dataset!J29-'dataset (2)'!J29 -> 0 | ... AE29: =+dataset!AE29-'dataset (2)'!AE29 -> 0
